atlas_rfp/__init__.py
atlas_rfp/__main__.py
atlas_rfp/atlas_parsing.py
atlas_rfp/models.py
atlas_rfp-0.1.8.dist-info/LICENSE
atlas_rfp-0.1.8.dist-info/METADATA
atlas_rfp-0.1.8.dist-info/WHEEL
atlas_rfp-0.1.8.dist-info/top_level.txt
atlas_rfp-0.1.8.dist-info/RECORD
