Metadata-Version: 2.1
Name: atlas-rfp
Version: 0.1.8
Summary: Programmatically access the Atlas RFP interface
Home-page: https://github.com/meson800/atlas-rfp
Author: Christopher Johnstone
Author-email: meson800@gmail.com
Project-URL: Bug Tracker, https://github.com/meson800/atlas-rfp/issues
Classifier: Development Status :: 4 - Beta
Classifier: Programming Language :: Python :: 3
Classifier: License :: OSI Approved :: MIT License
Classifier: Operating System :: OS Independent
Classifier: Topic :: Internet :: WWW/HTTP :: Session
Requires-Python: >=3.7
License-File: LICENSE
Requires-Dist: beautifulsoup4
Requires-Dist: touchstone-auth >=0.5.1
Requires-Dist: pydantic
Requires-Dist: py-moneyed
